LICENSE
README.md
setup.py
aspi/__init__.py
aspi.egg-info/PKG-INFO
aspi.egg-info/SOURCES.txt
aspi.egg-info/dependency_links.txt
aspi.egg-info/not-zip-safe
aspi.egg-info/requires.txt
aspi.egg-info/top_level.txt
aspi/drr/__init__.py
aspi/drr/bins.py
aspi/drr/drr3d.py
aspi/drr/drr3d_win.py
aspi/drr/drr5d.py
aspi/drr/genmask.py
aspi/drr/localfun.py
aspi/drr/utils.py
aspi/drr/window.py
aspi/ekfmm/__init__.py
aspi/ekfmm/fmm.py
aspi/ekfmm/fmmvti.py
aspi/ekfmm/stream.py
aspi/ekfmm/test.py
aspi/ekfmm/tomo.py
aspi/ekfmm/src/eikonal.c
aspi/ekfmm/src/eikonalvti.c
aspi/general/__init__.py
aspi/general/snr.py
aspi/npre/__init__.py
aspi/npre/npre3d.py
aspi/npre/tf.py
aspi/npre/src/npre3d.c
aspi/npre/src/npre_alloc.c
aspi/npre/src/npre_alloc.h
aspi/npre/src/npre_cdivn.c
aspi/npre/src/npre_cdivn.h
aspi/npre/src/npre_conjgrad.c
aspi/npre/src/npre_conjgrad.h
aspi/npre/src/npre_decart.c
aspi/npre/src/npre_decart.h
aspi/npre/src/npre_dtype.h
aspi/npre/src/npre_fft1.c
aspi/npre/src/npre_fxynpre.c
aspi/npre/src/npre_fxynpre.h
aspi/npre/src/npre_kissfft.c
aspi/npre/src/npre_kissfft.h
aspi/npre/src/npre_komplex.c
aspi/npre/src/npre_komplex.h
aspi/npre/src/npre_memcpy.c
aspi/npre/src/npre_memcpy.h
aspi/npre/src/npre_ntriangle.c
aspi/npre/src/npre_ntriangle.h
aspi/npre/src/npre_ntrianglen.c
aspi/npre/src/npre_ntrianglen.h
aspi/npre/src/npre_triangle.c
aspi/npre/src/npre_triangle.h
aspi/npre/src/npre_trianglen.c
aspi/npre/src/npre_trianglen.h
aspi/npre/src/npre_win.c
aspi/npre/src/npre_win.h
aspi/npre/src/tf.c
aspi/ntfa/__init__.py
aspi/ntfa/ntfa.py
aspi/ntfa/readwrite.py
aspi/ntfa/src/main.c
aspi/ntfa/src/ntfa_alloc.c
aspi/ntfa/src/ntfa_alloc.h
aspi/ntfa/src/ntfa_blas.c
aspi/ntfa/src/ntfa_blas.h
aspi/ntfa/src/ntfa_conjgrad.c
aspi/ntfa/src/ntfa_conjgrad.h
aspi/ntfa/src/ntfa_decart.c
aspi/ntfa/src/ntfa_decart.h
aspi/ntfa/src/ntfa_divnnsc.c
aspi/ntfa/src/ntfa_divnnsc.h
aspi/ntfa/src/ntfa_ntriangle.c
aspi/ntfa/src/ntfa_ntriangle.h
aspi/ntfa/src/ntfa_ntrianglen.c
aspi/ntfa/src/ntfa_ntrianglen.h
aspi/ntfa/src/ntfa_triangle.c
aspi/ntfa/src/ntfa_triangle.h
aspi/ntfa/src/ntfa_weight2.c
aspi/ntfa/src/ntfa_weight2.h
aspi/ortho/__init__.py
aspi/ortho/divne.py
